clogsec/__init__.py
clogsec/core.py
clogsec/crypto.py
clogsec/crypto.so
clogsec/decrypt_log.py
clogsec/filters.py
clogsec/formatters.py
clogsec/key_manager.py
clogsec/levels.py
clogsec-1.0.0.dist-info/METADATA
clogsec-1.0.0.dist-info/WHEEL
clogsec-1.0.0.dist-info/top_level.txt
clogsec-1.0.0.dist-info/RECORD
