Metadata-Version: 2.4
Name: clogsec
Version: 1.0.0
Summary: Secure logging with encryption and validation.
Author: crownie
Author-email: crondenice@atomicmail.io
License: Apache License 2.0
Requires-Dist: pycryptodome>=3.0.0
Requires-Dist: colorama>=0.1.1
Dynamic: author
Dynamic: author-email
Dynamic: description
Dynamic: description-content-type
Dynamic: license
Dynamic: requires-dist
Dynamic: summary
